{
  "values": [
    {
      "key": "award_achievement",
      "shortLabel": "AA",
      "label": "Award/Achievement",
      "type": "accomplishment"
    },
    {
      "key": "organized_event",
      "shortLabel": "OE",
      "label": "Organized Event",
      "type": "accomplishment"
    },
    {
      "key": "editorship",
      "shortLabel": "ED",
      "label": "Editorship",
      "type": "accomplishment"
    },
    {
      "key": "project_competitive",
      "shortLabel": "CP",
      "label": "Competitive Project",
      "type": "project"
    },
    {
      "key": "project_industrial",
      "shortLabel": "IP",
      "label": "Industrial Project",
      "type": "project"
    },
    {
      "key": "patent",
      "shortLabel": "PA",
      "label": "Patent",
      "type": "patent"
    },
    {
      "key": "project_agreement",
      "shortLabel": "AG",
      "label": "Agreement",
      "type": "project"
    }, {
      "key": "phd_lecture",
      "shortLabel": "PL",
      "label": "PhD lecture",
      "type": "training_module"
    }, {
      "key": "summer_winter_school_lecture",
      "shortLabel": "SWSL",
      "label": "Summer/Winter school lecture",
      "type": "training_module"
    }
  ]
}
